ovos_utterance_corrections_plugin-0.1.2.dist-info/licenses/LICENSE
ovos_utterance_corrections_transformer/__init__.py
ovos_utterance_corrections_transformer/version.py
ovos_utterance_corrections_plugin-0.1.2.dist-info/METADATA
ovos_utterance_corrections_plugin-0.1.2.dist-info/WHEEL
ovos_utterance_corrections_plugin-0.1.2.dist-info/entry_points.txt
ovos_utterance_corrections_plugin-0.1.2.dist-info/top_level.txt
ovos_utterance_corrections_plugin-0.1.2.dist-info/zip-safe
ovos_utterance_corrections_plugin-0.1.2.dist-info/RECORD
