Metadata-Version: 2.4
Name: ovos_utterance_corrections_plugin
Version: 0.1.2
Home-page: https://github.com/OpenVoiceOS/ovos-utterance-corrections-plugin
Author: jarbasai
Author-email: jarbasai@mailfence.com
License: apache-2.0
Classifier: Development Status :: 3 - Alpha
Classifier: Intended Audience :: Developers
Classifier: Topic :: Text Processing :: Linguistic
Classifier: License :: OSI Approved :: Apache Software License
Classifier: Programming Language :: Python :: 3.4
Classifier: Programming Language :: Python :: 3.5
Classifier: Programming Language :: Python :: 3.6
License-File: LICENSE
Requires-Dist: ovos-plugin-manager<3.0.0,>=0.0.1
Dynamic: author
Dynamic: author-email
Dynamic: classifier
Dynamic: home-page
Dynamic: license
Dynamic: license-file
Dynamic: requires-dist
